HISTORY.txt
LICENSE.txt
README.txt
email_backport-configure.zcml
setup.py
email_backport/__init__.py
email_backport/_parseaddr.py
email_backport/base64mime.py
email_backport/charset.py
email_backport/encoders.py
email_backport/errors.py
email_backport/feedparser.py
email_backport/generator.py
email_backport/header.py
email_backport/iterators.py
email_backport/message.py
email_backport/parser.py
email_backport/quoprimime.py
email_backport/utils.py
email_backport.egg-info/PKG-INFO
email_backport.egg-info/SOURCES.txt
email_backport.egg-info/SOURCES.txt~
email_backport.egg-info/dependency_links.txt
email_backport.egg-info/entry_points.txt
email_backport.egg-info/namespace_packages.txt
email_backport.egg-info/not-zip-safe
email_backport.egg-info/requires.txt
email_backport.egg-info/top_level.txt
email_backport/mime/__init__.py
email_backport/mime/application.py
email_backport/mime/audio.py
email_backport/mime/base.py
email_backport/mime/image.py
email_backport/mime/message.py
email_backport/mime/multipart.py
email_backport/mime/nonmultipart.py
email_backport/mime/text.py
email_backport/test/__init__.py
email_backport/test/test_email.py
email_backport/test/test_email_codecs.py
email_backport/test/test_email_codecs_renamed.py
email_backport/test/test_email_renamed.py
email_backport/test/test_email_torture.py
email_backport/test/data/PyBanner048.gif
email_backport/test/data/audiotest.au
email_backport/test/data/msg_01.txt
email_backport/test/data/msg_02.txt
email_backport/test/data/msg_03.txt
email_backport/test/data/msg_04.txt
email_backport/test/data/msg_05.txt
email_backport/test/data/msg_06.txt
email_backport/test/data/msg_07.txt
email_backport/test/data/msg_08.txt
email_backport/test/data/msg_09.txt
email_backport/test/data/msg_10.txt
email_backport/test/data/msg_11.txt
email_backport/test/data/msg_12.txt
email_backport/test/data/msg_12a.txt
email_backport/test/data/msg_13.txt
email_backport/test/data/msg_14.txt
email_backport/test/data/msg_15.txt
email_backport/test/data/msg_16.txt
email_backport/test/data/msg_17.txt
email_backport/test/data/msg_18.txt
email_backport/test/data/msg_19.txt
email_backport/test/data/msg_20.txt
email_backport/test/data/msg_21.txt
email_backport/test/data/msg_22.txt
email_backport/test/data/msg_23.txt
email_backport/test/data/msg_24.txt
email_backport/test/data/msg_25.txt
