Metadata-Version: 1.0
Name: email-backport
Version: 4.0.3b
Summary: A backport of the newest Python 2.x email module to >= Python 2.3
Home-page: http://www.nidelven-it.no/d
Author: Morten W. Petersen
Author-email: info@nidelven-it.no
License: Python Software Foundation License / Python License (CNRI Python License) and BSD
Keywords: python email backport
Platform: UNKNOWN
Classifier: Programming Language :: Python
Classifier: License :: OSI Approved :: Python License (CNRI Python License)
Classifier: License :: OSI Approved :: Python Software Foundation License
